{
  "adapters": [
    "google_trends"
  ],
  "sliced_spec": {
    "id": "global-tech-earnings-momentum",
    "name": "Global Tech Earnings Momentum",
    "frequency": "weekly",
    "universe": [
      "XLK"
    ],
    "entry_exit": {
      "entry": "If Google Trends search interest for tech earnings reports rises 20% above the prior 4-week average",
      "exit": "After 2 weeks or when search interest falls below 10% above the prior 4-week average"
    },
    "signal_logic": {
      "trigger": {
        "condition": "Google Trends search interest for tech earnings reports rises 20% above the prior 4-week average"
      }
    },
    "position_sizing": {
      "allocation_per_signal": "5%",
      "max_total_exposure": "20%"
    },
    "data_sources": {
      "google_trends": {
        "metric": "weekly search interest for tech company earnings reports",
        "adapter": "google_trends",
        "api": "weekly",
        "notes": ""
      }
    },
    "adapter_contracts": {
      "google_trends": {
        "func": "fetch_google_trends",
        "allowed_kwargs": [
          "keyword",
          "days_back"
        ],
        "returns": [
          "date",
          "interest"
        ]
      }
    }
  }
}